[
  {
    "bbox": [
      783,
      584,
      846,
      646
    ],
    "center_px": [
      814,
      615
    ],
    "avg_depth_m": 1.652,
    "x": 0.443,
    "y": 0.657,
    "z": 1.652,
    "label": "target_1"
  },
  {
    "bbox": [
      653,
      477,
      716,
      539
    ],
    "center_px": [
      684,
      508
    ],
    "avg_depth_m": 2.353,
    "x": 0.156,
    "y": 0.544,
    "z": 2.353,
    "label": "target_2"
  },
  {
    "bbox": [
      505,
      428,
      568,
      490
    ],
    "center_px": [
      536,
      459
    ],
    "avg_depth_m": 2.818,
    "x": -0.462,
    "y": 0.437,
    "z": 2.818,
    "label": "target_3"
  },
  {
    "bbox": [
      370,
      402,
      432,
      464
    ],
    "center_px": [
      401,
      433
    ],
    "avg_depth_m": 3.076,
    "x": -1.15,
    "y": 0.352,
    "z": 3.076,
    "label": "target_4"
  },
  {
    "bbox": [
      716,
      270,
      736,
      290
    ],
    "center_px": [
      726,
      280
    ],
    "avg_depth_m": 2.784,
    "x": 0.366,
    "y": -0.344,
    "z": 2.784,
    "label": "human"
  }
]